opencontainers/__init__.py
opencontainers/logger.py
opencontainers/struct.py
opencontainers/version.py
opencontainers/digest/__init__.py
opencontainers/digest/algorithm.py
opencontainers/digest/digest.py
opencontainers/digest/digester.py
opencontainers/digest/exceptions.py
opencontainers/digest/verifiers.py
opencontainers/distribution/__init__.py
opencontainers/distribution/specs.py
opencontainers/distribution/reggie/README.md
opencontainers/distribution/reggie/__init__.py
opencontainers/distribution/reggie/client.py
opencontainers/distribution/reggie/config.py
opencontainers/distribution/reggie/defaults.py
opencontainers/distribution/reggie/request.py
opencontainers/distribution/reggie/response.py
opencontainers/distribution/v1/__init__.py
opencontainers/distribution/v1/error.py
opencontainers/distribution/v1/repository.py
opencontainers/distribution/v1/tags.py
opencontainers/image/__init__.py
opencontainers/image/specs.py
opencontainers/image/v1/__init__.py
opencontainers/image/v1/annotations.py
opencontainers/image/v1/config.py
opencontainers/image/v1/descriptor.py
opencontainers/image/v1/index.py
opencontainers/image/v1/layout.py
opencontainers/image/v1/manifest.py
opencontainers/image/v1/mediatype.py
opencontainers/tests/__init__.py
opencontainers/tests/mock_server.py
opencontainers/tests/test_algorithm.py
opencontainers/tests/test_config.py
opencontainers/tests/test_descriptor.py
opencontainers/tests/test_digest.py
opencontainers/tests/test_distribution.py
opencontainers/tests/test_imageindex.py
opencontainers/tests/test_imagelayout.py
opencontainers/tests/test_manifest.py
opencontainers/tests/test_struct.py
opencontainers/tests/test_verifiers.py
opencontainers-0.0.15.dist-info/LICENSE
opencontainers-0.0.15.dist-info/METADATA
opencontainers-0.0.15.dist-info/WHEEL
opencontainers-0.0.15.dist-info/top_level.txt
opencontainers-0.0.15.dist-info/RECORD
