Metadata-Version: 2.1
Name: opencontainers
Version: 0.0.15
Summary: Python module for oci specifications
Home-page: http://github.com/vsoch/oci-python
Author: Vanessa Sochat
Author-email: vsoch@users.noreply.github.com
Maintainer: Vanessa Sochat
Maintainer-email: vsoch@users.noreply.github.com
License: LICENSE
Keywords: open containers,oci
Classifier: Intended Audience :: Science/Research
Classifier: Intended Audience :: Developers
Classifier: Programming Language :: Python
Classifier: Topic :: Software Development
Classifier: Topic :: Scientific/Engineering
Classifier: Operating System :: Unix
Classifier: Programming Language :: Python :: 3
License-File: LICENSE
